ryomath_4/init.py
ryomath_4/multiply.py
ryomath_4-0.1.0.dist-info/METADATA
ryomath_4-0.1.0.dist-info/WHEEL
ryomath_4-0.1.0.dist-info/top_level.txt
ryomath_4-0.1.0.dist-info/RECORD
